PyBioQuanta/__init__.py
PyBioQuanta/fasta_reader.py
PyBioQuanta/gc_calculator.py
PyBioQuanta/motif_finder.py
PyBioQuanta/random_dna_gen.py
PyBioQuanta/seq_reverser.py
PyBioQuanta/simple_translator.py
PyBioQuanta-0.1.1.dist-info/LICENSE
PyBioQuanta-0.1.1.dist-info/METADATA
PyBioQuanta-0.1.1.dist-info/WHEEL
PyBioQuanta-0.1.1.dist-info/top_level.txt
PyBioQuanta-0.1.1.dist-info/RECORD
