Metadata-Version: 2.1
Name: PyBioQuanta
Version: 0.1.1
Summary: PyBioQuanta: A small bioinformatics toolkit with 6 essential tools.
Author: Md. Ismiel Hossen Abir
Author-email: ismielabir1971@gmail.com
License: MIT
Classifier: Programming Language :: Python :: 3
Classifier: License :: OSI Approved :: MIT License
Classifier: Operating System :: OS Independent
Classifier: Topic :: Scientific/Engineering :: Bio-Informatics
Requires-Python: >=3.6
License-File: LICENSE
